README
setup.py
setup.pyc
src/bbicon/__init__.py
src/bbicon/bbicon.py
src/bbicon/bbicon_qrc.py
src/bbicon/tests.py
src/buildboticon.egg-info/PKG-INFO
src/buildboticon.egg-info/SOURCES.txt
src/buildboticon.egg-info/dependency_links.txt
src/buildboticon.egg-info/entry_points.txt
src/buildboticon.egg-info/requires.txt
src/buildboticon.egg-info/top_level.txt
src/buildboticon.egg-info/zip-safe