Metadata-Version: 1.0
Name: buildboticon
Version: 0.3.2
Summary: A buildbot monitoring utility
Home-page: http://bitbucket.org/marcusl/buildboticon
Author: Marcus Lindblom
Author-email: macke@yar.nu
License: GPL 3.0
Download-URL: http://packages.python.org/buildboticon
Keywords: buildbot systemtray pyqt
Platform: UNKNOWN
Classifier: Development Status :: 4 - Beta
Classifier: Intended Audience :: Developers
Classifier: Topic :: Utilities
Classifier: Topic :: Software Development :: Build Tools
Classifier: Topic :: Desktop Environment
Classifier: License :: OSI Approved :: GNU General Public License (GPL)
